README.md
setup.py
enduhub_downloader/__init__.py
enduhub_downloader/__main__.py
enduhub_downloader/best_result.py
enduhub_downloader/downloader.py
enduhub_downloader/event_type_group.py
enduhub_downloader/race_result.py
enduhub_downloader/runner.py
enduhub_downloader.egg-info/PKG-INFO
enduhub_downloader.egg-info/SOURCES.txt
enduhub_downloader.egg-info/dependency_links.txt
enduhub_downloader.egg-info/not-zip-safe
enduhub_downloader.egg-info/requires.txt
enduhub_downloader.egg-info/top_level.txt