Metadata-Version: 1.0
Name: enduhub-downloader
Version: 0.2
Summary: Download  run results from https://enduhub.com/
Home-page: https://github.com/mojek/enduhub_downloader
Author: Michał Mojek
Author-email: m.mojek@gmail.com
License: MIT
Platform: UNKNOWN
